dabest/__init__.py
dabest/_api.py
dabest/_bootstrap_tools.py
dabest/_dabest_object.py
dabest/_delta_objects.py
dabest/_effsize_objects.py
dabest/_modidx.py
dabest/forest_plot.py
dabest/misc_tools.py
dabest/multi.py
dabest/plot_tools.py
dabest/plotter.py
dabest/_stats_tools/__init__.py
dabest/_stats_tools/confint_1group.py
dabest/_stats_tools/confint_2group_diff.py
dabest/_stats_tools/effsize.py
dabest/_stats_tools/precompile.py
dabest-2025.10.20.dist-info/licenses/LICENSE
dabest-2025.10.20.dist-info/METADATA
dabest-2025.10.20.dist-info/WHEEL
dabest-2025.10.20.dist-info/entry_points.txt
dabest-2025.10.20.dist-info/top_level.txt
dabest-2025.10.20.dist-info/RECORD
