Metadata-Version: 2.4
Name: dabest
Version: 2025.10.20
Summary: Data Analysis and Visualization using Bootstrap-Coupled Estimation.
Home-page: https://github.com/acclab/DABEST-python
Author: Joses W. Ho
Author-email: joseshowh@gmail.com
License: Apache Software License 2.0
Project-URL: Documentation, https://acclab.github.io/DABEST-python
Keywords: nbdev jupyter notebook python
Classifier: Development Status :: 4 - Beta
Classifier: Intended Audience :: Developers
Classifier: Natural Language :: English
Classifier: Programming Language :: Python :: 3.10
Classifier: Programming Language :: Python :: 3.11
Classifier: Programming Language :: Python :: 3.12
Classifier: Programming Language :: Python :: 3.13
Classifier: License :: OSI Approved :: Apache Software License
Requires-Python: >=3.10
License-File: LICENSE
Requires-Dist: fastcore
Requires-Dist: pandas~=2.2.3
Requires-Dist: numpy~=2.1.0
Requires-Dist: matplotlib~=3.10.0
Requires-Dist: seaborn~=0.13.2
Requires-Dist: scipy~=1.15.2
Requires-Dist: numba~=0.61.0
Requires-Dist: datetime
Requires-Dist: statsmodels
Requires-Dist: lqrt
Requires-Dist: tqdm
Provides-Extra: dev
Requires-Dist: pytest~=8.3.4; extra == "dev"
Requires-Dist: pytest-mpl~=0.17.0; extra == "dev"
Dynamic: author
Dynamic: author-email
Dynamic: classifier
Dynamic: description
Dynamic: description-content-type
Dynamic: home-page
Dynamic: keywords
Dynamic: license
Dynamic: license-file
Dynamic: project-url
Dynamic: provides-extra
Dynamic: requires-dist
Dynamic: requires-python
Dynamic: summary
